easyotp/__init__.py
easyotp/client.py
easyotp/exceptions.py
easyotp/models.py
easyotp/py.typed
easyotp-1.0.0.dist-info/licenses/LICENSE
easyotp-1.0.0.dist-info/METADATA
easyotp-1.0.0.dist-info/WHEEL
easyotp-1.0.0.dist-info/top_level.txt
easyotp-1.0.0.dist-info/RECORD
