Metadata-Version: 2.4
Name: easyotp
Version: 1.0.0
Summary: Python SDK for EasyOTP - Send and verify OTP codes via SMS, Email, and Voice
Author-email: EasyOTP <support@easyotp.dev>
License: MIT
Project-URL: Homepage, https://easyotp.dev
Project-URL: Documentation, https://docs.easyotp.dev
Project-URL: Repository, https://github.com/easyotp/easyotp-python
Keywords: otp,sms,email,voice,verification,2fa,mfa
Classifier: Development Status :: 4 - Beta
Classifier: Intended Audience :: Developers
Classifier: License :: OSI Approved :: MIT License
Classifier: Programming Language :: Python :: 3
Classifier: Programming Language :: Python :: 3.7
Classifier: Programming Language :: Python :: 3.8
Classifier: Programming Language :: Python :: 3.9
Classifier: Programming Language :: Python :: 3.10
Classifier: Programming Language :: Python :: 3.11
Classifier: Programming Language :: Python :: 3.12
Requires-Python: >=3.7
License-File: LICENSE
Requires-Dist: requests>=2.28.0
Dynamic: license-file
